dyad/__init__.py
dyad/apply_code.py
dyad/apply_code_entities.py
dyad/chat.py
dyad/dyad-extension.toml
dyad/dyad_pro.py
dyad/file_tree.py
dyad/pad.py
dyad/pad_logic.py
dyad/suggestions.py
dyad/todo_parser.py
dyad/version.py
dyad/workspace_util.py
dyad/agent_api/__init__.py
dyad/agent_api/agent.py
dyad/agent_api/agent_context.py
dyad/agents/__init__.py
dyad/agents/default_agent.py
dyad/agents/py.typed
dyad/agents/reasoner_agent.py
dyad/agents/search_agent.py
dyad/agents/vanilla_agent.py
dyad/agents/tools/__init__.py
dyad/agents/tools/code_edit.py
dyad/agents/tools/code_search.py
dyad/agents/tools/perplexity_api.py
dyad/agents/tools/web_search.py
dyad/api/__init__.py
dyad/api/api_base.py
dyad/api/api_urls.py
dyad/code_edit/__init__.py
dyad/code_edit/py.typed
dyad/code_edit/simple_handler.py
dyad/code_edit/util.py
dyad/constants/__init__.py
dyad/entities/__init__.py
dyad/entities/embedder_id.py
dyad/extension/__init__.py
dyad/extension/extension_registry.py
dyad/indexing/__init__.py
dyad/indexing/file_extensions.py
dyad/indexing/file_indexing.py
dyad/indexing/file_update.py
dyad/indexing/lance_store.py
dyad/indexing/semantic_search_store.py
dyad/indexing/embeddings/__init__.py
dyad/indexing/embeddings/embedding_provider.py
dyad/language_model/__init__.py
dyad/language_model/language_model.py
dyad/language_model/language_model_clients.py
dyad/language_model_registry/__init__.py
dyad/language_model_registry/anthropic.py
dyad/logging/__init__.py
dyad/logging/analytics.py
dyad/logging/llm_calls.py
dyad/logging/logging.py
dyad/logging/logs_sql_engine.py
dyad/message_cache/__init__.py
dyad/prompts/__init__.py
dyad/prompts/prompts.py
dyad/public/__init__.py
dyad/public/agent_step.py
dyad/public/chat_message.py
dyad/public/input.py
dyad/public/part.py
dyad/settings/__init__.py
dyad/settings/user_settings.py
dyad/settings/workspace_settings.py
dyad/status/__init__.py
dyad/status/status.py
dyad/status/status_tracker.py
dyad/storage/__init__.py
dyad/storage/db.py
dyad_core-0.1.7.dist-info/METADATA
dyad_core-0.1.7.dist-info/WHEEL
dyad_core-0.1.7.dist-info/RECORD
