Metadata-Version: 2.4
Name: dyad-core
Version: 0.1.7
Summary: Add your description here
Requires-Python: >=3.10
Requires-Dist: anthropic>=0.42.0
Requires-Dist: colorlog>=6.8.2
Requires-Dist: filelock>=3.17.0
Requires-Dist: instructor>=1.7.2
Requires-Dist: lancedb>=0.21.2
Requires-Dist: numpy>=2.2.1
Requires-Dist: openai>=1.58.1
Requires-Dist: pathspec>=0.12.1
Requires-Dist: posthog>=3.10.0
Requires-Dist: pydantic>=2.9.2
Requires-Dist: pylance>=0.25.1
Requires-Dist: python-frontmatter>=1.1.0
Requires-Dist: requests>=2.32.3
Requires-Dist: sqlalchemy>=2.0.35
Requires-Dist: sqlmodel>=0.0.22
Requires-Dist: tantivy>=0.22.0
Requires-Dist: toml>=0.10.2
Requires-Dist: tree-sitter-languages>=1.10.2
Requires-Dist: tree-sitter==0.21.3
Requires-Dist: watchfiles>=1.0.3
